meta_info/__init__.py
meta_info/meta_check.py
meta_info/meta_html.py
meta_info/meta_info.py
meta_info/meta_info_unittests.py
meta_info/meta_json_schema.py
meta_info/meta_schema.py
meta_info/meta_tool.py
meta_info_tools/__init__.py
meta_info_tools/meta_check.py
meta_info_tools/meta_html.py
meta_info_tools/meta_info.py
meta_info_tools/meta_info_unittests.py
meta_info_tools/meta_json_schema.py
meta_info_tools/meta_schema.py
meta_info_tools/meta_tool.py
meta_info_tools/test_meta_check.py
meta_info_tools/test_meta_html.py
meta_info_tools/test_meta_info.py
meta_info_tools/test_meta_json_schema.py
meta_info_tools/test_meta_schema.py
meta_info_tools-0.0.3.dist-info/LICENSE
meta_info_tools-0.0.3.dist-info/METADATA
meta_info_tools-0.0.3.dist-info/WHEEL
meta_info_tools-0.0.3.dist-info/top_level.txt
meta_info_tools-0.0.3.dist-info/RECORD
