Metadata-Version: 2.1
Name: meta-info-tools
Version: 0.0.3
Summary: Tools to handle meta_info
Home-page: https://github.com/fawzi/meta-info-tools
Author: Fawzi Mohamed
Author-email: fawzi@kitabi.eu
License: UNKNOWN
Platform: UNKNOWN
Classifier: Programming Language :: Python :: 3
Classifier: License :: OSI Approved :: MIT License
Classifier: Operating System :: OS Independent
Requires-Python: >=3.6
Requires-Dist: Markdown (>=3.1.1)
Requires-Dist: pydantic (>=0.28)
Requires-Dist: jsonschema
